{"rN7XvJuD+cWV6tP6K65XGw==":"mbr.png","onfPb9gWqtqjrTGSYuXLag==":"gau-1139x1139.jpg","iulvtFKxu4pIEbyrz4rIUw==":"front-1280x738.jpg","M3aPt57E2LZax+dpMIDFDg==":"img-20200706-wa0001-492x615.jpg","2OQK2/2jRxc8/rAAHdQYxw==":"gau-3-249x221.jpeg","MHnoUkukAE1IET36a7KElw==":"logo-172x16.png","eSdLWs77vxRu2k8bcDSXaw==":"logo-232x37.png","rkDi/t9PrkOH+p8jtok0eg==":"logo-1-232x37.png","l7SEc6OlfnFm+2FnOzpmBA==":"logo-2-232x37.png","klWa9qtSaN8iYHNyiCtiqQ==":"dialogo-163x55.png","Mt8qBIub5SBRP0PEnENfYQ==":"logo-360x56.png","YnFdJN15DgWaT9zZLWHbJw==":"logo-782x117.png","G1zk2rDigkmyrU25Fd8KcQ==":"logo-812x122.png","BpQmoYVxXbZ0bLamrp8aAA==":"logo-809x148.png","nXdHoiuQe+745jjFXBbmbQ==":"logo-664x121.png","hjQmUJLas2/+iy70OI4LLA==":"logo-668x122.png","+j4tSmwM7EbmkxTja0qlKw==":"logo-666x122.png","98DOTPFj+YlvZSit+nb61g==":"logo-409x148.png","4aHKCN7X/PDXxlUKca7AmA==":"front-1228x800.png","RBY0+FF6Fhd1XvT2tU/uDQ==":"front-1-1228x800.png","V5V25tbo8ostwM1xi3hnZA==":"front-1-1280x738.jpg","4f8zuC/FY3MMz28eLgZtuA==":"front-1000x700.jpg","1USabND/iugksuBMU6mUqg==":"front-1-1000x700.jpg","QuVTi7m1Lfn1ZycO7zdOxA==":"front-2-1000x700.jpg","2/lRtQGbb3zrIp//H/NFGg==":"front-3-1000x700.jpg","yt3MuRqdxHezKjyb1w3F6w==":"front-4-1000x700.jpg","9mU61+2FwckS63c7RW08Qg==":"front-5-1000x700.jpg","4waFDw5DnUVNxzQK7jGqcA==":"front-6-1000x700.jpg","DIjjUg24VRVaiKYqTqshAw==":"front-2-1228x800.png","z2URo/rBtD7YqCbRfXDwyg==":"front-3-1228x800.png","C7qUtJh99JAJHTRbzZTCSw==":"gau%20(2)-1000x577.jpg","N0AUg6TbEQFGYM74iPIIiw==":"gau%20(2)-1000x577.jpg","icDnEv7qtmd3hPNj9XQKzA==":"gau%20(2)-1000x577.jpg","VgIxS8HI+nlo2cuholrYZQ==":"gau%20(2)-1000x531.jpg","WTeQS5b6m668UtRW5n8THg==":"gau%20(2)-1000x503.jpg","ERqz777/U9iDAA79xhYjkA==":"gau%20(2)-1000x461.jpg","ggpTPFcQ5xLIwXvNHU1A1w==":"gau%20(2)-1000x461.jpg","5Gju6HDkfYshH55ZQmSKNA==":"gau%20(2)-1000x461.jpeg","PZKhHZ+SQx4p5dBB8Vgf5Q==":"gau%20(2)-1000x461.jpg","4cD8q9D1T9u7yggb4BuuQQ==":"gau%20(2)-1000x461.jpeg","EKqCR7yrFiaZXTAM8NOUsg==":"gau%20(2)-1000x461.jpeg","wy8Kl7aemchOHkyA1JnMMg==":"gau%20(2)-1000x461.jpeg","I5rigPI5wzm6nDGPZfX8aQ==":"gau-(2)-1000x461.jpeg","Cf4XP1XJerHxZEbPwA/L7Q==":"gau1-1000x461.jpeg","Y+ISKJJFuhSwZ3P0lovJeg==":"gau1-1-1000x461.jpeg","kn8Mbs8QWzUxIb+ZZfanhA==":"gau1-2-1000x461.jpeg","MzzWUgaaC9okEmZJjlViUQ==":"gau1-3-1000x461.jpeg","ssBZ5ry7UZyDKv9ixWjo0w==":"gau3-1000x461.jpeg","nEB1gwqif0CLmHS2eHpqpQ==":"gau1-4-1000x461.jpeg","2dgVNrwjSE26vrBNj+f2Fw==":"gau1-5-1000x461.jpeg","3nOg31iPABV0iJepExqNog==":"logo-362x131.png","MEa4oYIiYfGqsx/Bt09bIQ==":"logo-358x130.png","JQVS9h81Fi5YcMJ5NtQ93g==":"gau1-1000x461.jpg","glTvM/USdHtqp79bzMGY0A==":"img-20200720-wa0003-1268x1268.jpg","+0fiYiXCL3QrXSulfy1UkA==":"img-20200716-wa0015-510x638.jpg","TNMsAPiDX86JJv9GbVP3Hw==":"img-20200716-wa0010-960x720.jpg","jJOKtugbyKOyxPCZHbg88g==":"img-20200716-wa0013-960x720.jpg","tA71P/7bc03DSSBJhhK6iw==":"img-20200716-wa0018-540x1200.jpg","mIIbxW0r7dEZSbMPwcoYdg==":"background2.jpg","SkHuCPT4lCVtHLpt/CDeCw==":"img-20200703-wa0007-1023x1280.jpg","ZmNNwfPtNKDB+bEpJ1cNAA==":"training-1115x503.png","Bmm5TnYLhM/OLFlq/9FhYQ==":"training-1000x461.jpg","WgSgJLoFCHdKZc8AtAYbXA==":"img-20200706-wa0000-485x960.jpg","51/bjq7QVjcDX/78dkQ2Ow==":"img-20200706-wa0002-720x960.jpg","763Z5ZlK0OMJ4w3Xxv1haQ==":"img-20200716-wa0021-824x1585.jpg","siiBfR+xuO0FVEYmop3y4w==":"img-20200716-wa0010-824x618.jpg","NdYFhhcBAxcr4pEGFotMng==":"schedule-824x1021.jpg","sAI0nBjBUIWTxE5ykSa1Dw==":"training-1-1000x461.jpg","Pkip3kUoHIKUtiA0h55A1A==":"schedule-1-824x1021.jpg","FP9qbLggxdGE4/yFC0z56Q==":"training-2-1000x461.jpg","2K2Lq2wP8OBHwiG6qDoblw==":"training-3-1000x461.jpg","3bA8PFdvU44WJi8rJ9G+2A==":"training-4-1000x461.jpg","TGExz959TG5vjVAd+Xu3sg==":"training-5-1000x461.jpg","75Ho1ax46BQjHpbD+w7VBQ==":"training-6-1000x461.jpg","J9GE3NwVLiUpZs0FhDXo/Q==":"ser-1000x461.jpg","ce8oaEYyjFWeHyBD9Mr0GA==":"img-20200716-wa0015-596x745.jpeg","mSNeu6gfGHU56OOW6rORGw==":"img-20200716-wa0015-1-596x745.jpeg","vkf/Z4QbGnR8HfikLcbDWw==":"img-20200716-wa0025-596x650.jpeg","UIuG5dZkWbDjyacKIyIhZw==":"img-20200716-wa0025-1-596x650.jpeg","F9GVIZwFgX4+x399bysqog==":"img-20200703-wa0009-596x745.jpeg","Tp3z2UH4wb3uUh6xHGo9Hg==":"img-20200716-wa0025-2-596x650.jpeg","O9A6tTfkArp0iayupbde3g==":"img-20200716-wa0025-3-596x650.jpeg","rqhazwHHrxpbihqWZkBHrA==":"img-20200716-wa0025-4-596x650.jpeg","1IQSEmiU40S64ZYubmgvwA==":"img-20200716-wa0025-5-596x650.jpeg","DWGoFUmNeEck1TRllUHKBA==":"img-20200716-wa0013-596x447.jpg","9758IccEExqVAoBkfzYMrQ==":"img-20200716-wa0013-596x447.jpeg","t4r6R0l5h94qcwOo0jVOtw==":"img-20200720-wa0005-596x596.jpeg","spA1uE1ms0Iw/p/kSrdkmg==":"img-20200720-wa0004-596x596.jpeg","yk9lAFtbx6LwfDI9JOlLzw==":"img-20200716-wa0021-646x1242.jpeg","KJHgBzFgQTDO4G6m4HG4Qg==":"schedule-646x801.jpg","6AlExur+i2x1FsjpyfdhPg==":"img-20200716-wa0008-1032x774.jpg","K14uvnKHs8bMh4uCHwL42g==":"img-20200716-wa0016-1080x1080.jpg"}